runtime_provisioner/__init__.py
runtime_provisioner/runtime_provisioner.py
runtime_provisioner-1.0.1.dist-info/licenses/LICENSE
runtime_provisioner-1.0.1.dist-info/METADATA
runtime_provisioner-1.0.1.dist-info/WHEEL
runtime_provisioner-1.0.1.dist-info/top_level.txt
runtime_provisioner-1.0.1.dist-info/RECORD
