Metadata-Version: 2.4
Name: runtime-provisioner
Version: 1.0.1
Summary: 运行时依赖自动下载器 - 自动下载和管理运行时依赖
Home-page: https://github.com/your-username/runtime-provisioner
Author: Runtime Provisioner Team
Author-email: Runtime Provisioner Team <contact@example.com>
License: MIT
Project-URL: Homepage, https://github.com/your-username/runtime-provisioner
Project-URL: Bug Reports, https://github.com/your-username/runtime-provisioner/issues
Project-URL: Source, https://github.com/your-username/runtime-provisioner
Keywords: download,dependencies,runtime,provisioner,automation
Classifier: Development Status :: 4 - Beta
Classifier: Intended Audience :: Developers
Classifier: License :: OSI Approved :: MIT License
Classifier: Operating System :: OS Independent
Classifier: Programming Language :: Python :: 3
Classifier: Programming Language :: Python :: 3.7
Classifier: Programming Language :: Python :: 3.8
Classifier: Programming Language :: Python :: 3.9
Classifier: Programming Language :: Python :: 3.10
Classifier: Programming Language :: Python :: 3.11
Classifier: Topic :: Software Development :: Libraries :: Python Modules
Classifier: Topic :: System :: Installation/Setup
Classifier: Topic :: Utilities
Requires-Python: >=3.7
License-File: LICENSE
Requires-Dist: wget>=3.2
Dynamic: author
Dynamic: home-page
Dynamic: license-file
Dynamic: requires-python
